README.md
setup.py
aiplat_acu_asr.egg-info/PKG-INFO
aiplat_acu_asr.egg-info/SOURCES.txt
aiplat_acu_asr.egg-info/dependency_links.txt
aiplat_acu_asr.egg-info/requires.txt
aiplat_acu_asr.egg-info/top_level.txt
baidu_acu_asr/__init__.py
baidu_acu_asr/asr_client.py
baidu_acu_asr/asr_client_factory.py
baidu_acu_asr/asr_product.py
baidu_acu_asr/audio_streaming_pb2.py
baidu_acu_asr/audio_streaming_pb2_grpc.py
baidu_acu_asr/client_demo.py
baidu_acu_asr/client_demo_directory_multi_process.py
baidu_acu_asr/client_demo_directory_multi_thread.py
baidu_acu_asr/client_demo_multi_thread.py
baidu_acu_asr/client_demo_simple.py
baidu_acu_asr/generic_client_interceptor.py
baidu_acu_asr/header_manipulator_client_interceptor.py
baidu_acu_asr/request_header_validator_interceptor.py