Metadata-Version: 2.1
Name: aiplat-acu-asr
Version: 2.0.6
Summary: asr grpc client
Home-page: https://github.com/baidubce/pie/tree/master/audio-streaming-client-python-sdk
Author: Baidu
Author-email: 1908131339@qq.com
License: Apache License
Keywords: baidu,asr,speech
Platform: UNKNOWN
Requires-Python: >=2.7
